doktarpy/__init__.py
doktarpy/doktarpy.py
doktarpy-0.0.2.dist-info/METADATA
doktarpy-0.0.2.dist-info/WHEEL
doktarpy-0.0.2.dist-info/top_level.txt
doktarpy-0.0.2.dist-info/RECORD
