Metadata-Version: 2.1
Name: doktarpy
Version: 0.0.2
Summary: Doktar GIS Python Operations
Home-page: https://github.com/doktargis/doktarpy
Author: Batuhan Kavlak
Author-email: batuhan.kavlak@doktar.com
License: UNKNOWN
Keywords: doktarpy
Platform: UNKNOWN
Classifier: Development Status :: 2 - Pre-Alpha
Classifier: Intended Audience :: Developers
Classifier: Natural Language :: English
Classifier: Programming Language :: Python :: 3
Classifier: Programming Language :: Python :: 3.5
Classifier: Programming Language :: Python :: 3.6
Classifier: Programming Language :: Python :: 3.7
Classifier: Programming Language :: Python :: 3.8
Requires-Python: >=3.5
